{"chunk_definitions":[{"row":25,"row_count":1,"visible":true,"expansion_state":0,"options":{"engine":"r","label":"setup","include":false},"document_id":"6866096F","chunk_id":"csetup_chunk","chunk_label":"setup"},{"row":65,"row_count":1,"visible":true,"expansion_state":0,"options":{"engine":"r","echo":false,"label":"unnamed-chunk-81"},"document_id":"6866096F","chunk_id":"czgmub7zh8op3","chunk_label":"unnamed-chunk-2"},{"row":94,"row_count":1,"visible":true,"expansion_state":0,"options":{"engine":"r","echo":false,"label":"unnamed-chunk-127"},"document_id":"6866096F","chunk_id":"c8qgfx9drojum","chunk_label":"unnamed-chunk-3"},{"row":116,"row_count":1,"visible":true,"expansion_state":0,"options":{"engine":"r","label":"unnamed-chunk-33"},"document_id":"6866096F","chunk_id":"czlaqhtvlx486","chunk_label":"unnamed-chunk-4"},{"row":145,"row_count":1,"visible":true,"expansion_state":1,"options":{"engine":"r","label":"unnamed-chunk-58"},"document_id":"6866096F","chunk_id":"c4ghmgoevufv9","chunk_label":"unnamed-chunk-5"},{"row":162,"row_count":1,"visible":true,"expansion_state":1,"options":{"engine":"r","echo":false,"label":"unnamed-chunk-63"},"document_id":"D4EEAFC8","chunk_id":"cy94ifj5hojkc","chunk_label":"unnamed-chunk-6"},{"row":177,"row_count":1,"visible":true,"expansion_state":0,"options":{"engine":"r","label":"unnamed-chunk-69"},"document_id":"6866096F","chunk_id":"cqxiw1ms5a8xd","chunk_label":"unnamed-chunk-7"},{"row":200,"row_count":1,"visible":true,"expansion_state":0,"options":{"engine":"r","label":"unnamed-chunk-124"},"document_id":"6866096F","chunk_id":"cbgmo2zokwuuo","chunk_label":"unnamed-chunk-8"},{"row":249,"row_count":1,"visible":true,"expansion_state":0,"options":{"engine":"r","label":"unnamed-chunk-76"},"document_id":"6866096F","chunk_id":"ch6gbexhsja1w","chunk_label":"unnamed-chunk-10"},{"row":271,"row_count":1,"visible":true,"expansion_state":0,"options":{"engine":"r","label":"unnamed-chunk-77"},"document_id":"6866096F","chunk_id":"c19j3j1ril0u6","chunk_label":"unnamed-chunk-11"},{"row":290,"row_count":1,"visible":true,"expansion_state":0,"options":{"engine":"r","label":"unnamed-chunk-80"},"document_id":"6866096F","chunk_id":"cx6rn64hv74mg","chunk_label":"unnamed-chunk-12"}],"doc_write_time":1636135971,"working_dir":null,"default_chunk_options":{}}